mymesh/__init__.py
mymesh/booleans.py
mymesh/contour.py
mymesh/converter.py
mymesh/curvature.py
mymesh/delaunay.py
mymesh/image.py
mymesh/implicit.py
mymesh/improvement.py
mymesh/mesh.py
mymesh/primitives.py
mymesh/quality.py
mymesh/rays.py
mymesh/register.py
mymesh/tree.py
mymesh/utils.py
mymesh/visualize.py
mymesh-0.3.0.dist-info/licenses/LICENSE.md
mymesh-0.3.0.dist-info/METADATA
mymesh-0.3.0.dist-info/WHEEL
mymesh-0.3.0.dist-info/top_level.txt
mymesh-0.3.0.dist-info/RECORD
