Metadata-Version: 2.4
Name: mymesh
Version: 0.3.0
Summary: Python code for generating and working with meshes.
Author-email: "Timothy O. Josephson" <toj@bu.edu>
License: MIT License
Project-URL: Documentation, https://bu-smbl.github.io/mymesh/
Keywords: mesh,scientific,engineering,mechanics,fem,fvm,finite elements,3D model
Classifier: Development Status :: 4 - Beta
Classifier: Programming Language :: Python
Classifier: Intended Audience :: Science/Research
Classifier: Topic :: Scientific/Engineering
Classifier: Topic :: Utilities
Classifier: License :: OSI Approved :: MIT License
Classifier: Programming Language :: Python :: 3
Classifier: Programming Language :: Python :: 3.8
Classifier: Programming Language :: Python :: 3.9
Classifier: Programming Language :: Python :: 3.10
Classifier: Programming Language :: Python :: 3.11
Classifier: Programming Language :: Python :: 3.12
Requires-Python: >=3.8
License-File: LICENSE.md
Requires-Dist: importlib-metadata; python_version < "3.8"
Requires-Dist: numpy>=1.20.0
Requires-Dist: scipy>=1.10.0
Requires-Dist: sympy>=1.11
Provides-Extra: all
Requires-Dist: meshio>=5.1.0; extra == "all"
Requires-Dist: numba>=0.60.0; extra == "all"
Requires-Dist: pydicom>=2.4.4; extra == "all"
Requires-Dist: tifffile>=2025.2.18; extra == "all"
Requires-Dist: opencv-python>=4.9.0.0; extra == "all"
Requires-Dist: vispy>=0.14.1; extra == "all"
Requires-Dist: matplotlib>=3.7.1; extra == "all"
Requires-Dist: pillow>=10.0.0; extra == "all"
Requires-Dist: jupyter_rfb>=0.4.2; extra == "all"
Requires-Dist: PyQt6>=6.2.3; extra == "all"
Requires-Dist: PyGlet>=2.0.10; extra == "all"
Requires-Dist: pyvista>=0.45.2; extra == "all"
Dynamic: license-file
